scikit_cars-0.20.dev3.dist-info/RECORD
scikit_cars-0.20.dev3.dist-info/WHEEL
scikit_cars-0.20.dev3.dist-info/top_level.txt
scikit_cars-0.20.dev3.dist-info/LICENSE.txt
scikit_cars-0.20.dev3.dist-info/METADATA
skimage/conftest.py
skimage/__init__.py
skimage/_build.py
skimage/setup.py
skimage/filters/_gabor.py
skimage/filters/ridges.py
skimage/filters/_multiotsu.cpython-310-darwin.so
skimage/filters/_multiotsu.pyx
skimage/filters/_sparse.py
skimage/filters/_median.py
skimage/filters/__init__.py
skimage/filters/thresholding.py
skimage/filters/edges.py
skimage/filters/_unsharp_mask.py
skimage/filters/_fft_based.py
skimage/filters/setup.py
skimage/filters/_rank_order.py
skimage/filters/lpi_filter.py
skimage/filters/_window.py
skimage/filters/_gaussian.py
skimage/filters/tests/test_median.py
skimage/filters/tests/test_fft_based.py
skimage/filters/tests/__init__.py
skimage/filters/tests/test_lpi_filter.py
skimage/filters/tests/test_gaussian.py
skimage/filters/tests/test_ridges.py
skimage/filters/tests/test_window.py
skimage/filters/tests/test_thresholding.py
skimage/filters/tests/test_correlate.py
skimage/filters/tests/test_edges.py
skimage/filters/tests/test_unsharp_mask.py
skimage/filters/tests/test_gabor.py
skimage/filters/rank/generic_cy.cpython-310-darwin.so
skimage/filters/rank/core_cy.pyx
skimage/filters/rank/core_cy_3d.cpython-310-darwin.so
skimage/filters/rank/percentile_cy.pyx
skimage/filters/rank/generic.py
skimage/filters/rank/bilateral_cy.pyx
skimage/filters/rank/__init__.py
skimage/filters/rank/core_cy.cpython-310-darwin.so
skimage/filters/rank/core_cy_3d.pyx
skimage/filters/rank/percentile_cy.cpython-310-darwin.so
skimage/filters/rank/generic_cy.pyx
skimage/filters/rank/core_cy_3d.pxd
skimage/filters/rank/bilateral.py
skimage/filters/rank/_percentile.py
skimage/filters/rank/bilateral_cy.cpython-310-darwin.so
skimage/filters/rank/core_cy.pxd
skimage/filters/rank/tests/__init__.py
skimage/filters/rank/tests/test_rank.py
skimage/metrics/_structural_similarity.py
skimage/metrics/__init__.py
skimage/metrics/_adapted_rand_error.py
skimage/metrics/_variation_of_information.py
skimage/metrics/_contingency_table.py
