Metadata-Version: 2.1
Name: scikit-cars
Version: 0.20.dev3
Summary: Fork of scikit-image including SAD in SLIC algorithm
Home-page: https://github.com/DamienBoildieu/scikit-image
Download-URL: https://github.com/DamienBoildieu/scikit-image
Maintainer: Damien Boildieu
Maintainer-email: damien.boildieu@unilim.fr
License: Modified BSD
Project-URL: Source Code, https://github.com/DamienBoildieu/scikit-image
Classifier: Development Status :: 4 - Beta
Classifier: Environment :: Console
Classifier: Intended Audience :: Developers
Classifier: Intended Audience :: Science/Research
Classifier: License :: OSI Approved :: BSD License
Classifier: Programming Language :: C
Classifier: Programming Language :: Python
Classifier: Programming Language :: Python :: 3
Classifier: Programming Language :: Python :: 3.8
Classifier: Programming Language :: Python :: 3.9
Classifier: Programming Language :: Python :: 3.10
Classifier: Programming Language :: Python :: 3 :: Only
Classifier: Topic :: Scientific/Engineering
Classifier: Operating System :: Microsoft :: Windows
Classifier: Operating System :: POSIX
Classifier: Operating System :: Unix
Classifier: Operating System :: MacOS
Requires-Python: >=3.8
License-File: LICENSE.txt
Requires-Dist: numpy (>=1.19)
Requires-Dist: scipy (>=1.5)
Requires-Dist: networkx (>=2.5)
Requires-Dist: pillow (>=9.0.1)
Requires-Dist: imageio (>=2.4.1)
Requires-Dist: tifffile (>=2019.7.26)
Requires-Dist: PyWavelets (>=1.1.1)
Requires-Dist: packaging (>=20.0)
Provides-Extra: data
Requires-Dist: pooch (>=1.3.0) ; extra == 'data'
Provides-Extra: docs
Requires-Dist: sphinx (>=1.8) ; extra == 'docs'
Requires-Dist: sphinx-gallery (>=0.10.1) ; extra == 'docs'
Requires-Dist: numpydoc (>=1.0) ; extra == 'docs'
Requires-Dist: sphinx-copybutton ; extra == 'docs'
Requires-Dist: pytest-runner ; extra == 'docs'
Requires-Dist: scikit-learn ; extra == 'docs'
Requires-Dist: matplotlib (>=3.3) ; extra == 'docs'
Requires-Dist: dask[array] (!=2.17.0,>=0.15.0) ; extra == 'docs'
Requires-Dist: cloudpickle (>=0.2.1) ; extra == 'docs'
Requires-Dist: pandas (>=0.23.0) ; extra == 'docs'
Requires-Dist: seaborn (>=0.7.1) ; extra == 'docs'
Requires-Dist: pooch (>=1.3.0) ; extra == 'docs'
Requires-Dist: tifffile (>=2020.5.30) ; extra == 'docs'
Requires-Dist: myst-parser ; extra == 'docs'
Requires-Dist: ipywidgets ; extra == 'docs'
Requires-Dist: plotly (>=4.14.0) ; extra == 'docs'
Requires-Dist: kaleido ; extra == 'docs'
Provides-Extra: optional
Requires-Dist: SimpleITK ; extra == 'optional'
Requires-Dist: astropy (>=3.1.2) ; extra == 'optional'
Requires-Dist: cloudpickle (>=0.2.1) ; extra == 'optional'
Requires-Dist: dask[array] (!=2.17.0,>=1.0.0) ; extra == 'optional'
Requires-Dist: matplotlib (>=3.3) ; extra == 'optional'
Requires-Dist: pooch (>=1.3.0) ; extra == 'optional'
Requires-Dist: pyamg ; extra == 'optional'
Provides-Extra: test
Requires-Dist: asv ; extra == 'test'
Requires-Dist: codecov ; extra == 'test'
Requires-Dist: flake8 ; extra == 'test'
Requires-Dist: matplotlib (>=3.3) ; extra == 'test'
Requires-Dist: pooch (>=1.3.0) ; extra == 'test'
Requires-Dist: pytest (>=5.2.0) ; extra == 'test'
Requires-Dist: pytest-cov (>=2.7.0) ; extra == 'test'
Requires-Dist: pytest-localserver ; extra == 'test'
Requires-Dist: pytest-faulthandler ; extra == 'test'
